statqa/__init__.py
statqa/analysis/__init__.py
statqa/analysis/bivariate.py
statqa/analysis/causal.py
statqa/analysis/temporal.py
statqa/analysis/univariate.py
statqa/cli/__init__.py
statqa/cli/main.py
statqa/exceptions.py
statqa/interpretation/__init__.py
statqa/interpretation/context.py
statqa/interpretation/formatter.py
statqa/metadata/__init__.py
statqa/metadata/enricher.py
statqa/metadata/parsers/__init__.py
statqa/metadata/parsers/base.py
statqa/metadata/parsers/csv.py
statqa/metadata/parsers/statistical.py
statqa/metadata/parsers/text.py
statqa/metadata/schema.py
statqa/py.typed
statqa/qa/__init__.py
statqa/qa/generator.py
statqa/qa/templates.py
statqa/types.py
statqa/utils/__init__.py
statqa/utils/io.py
statqa/utils/logging.py
statqa/utils/stats.py
statqa/visualization/__init__.py
statqa/visualization/plots.py
statqa/visualization/themes.py
statqa-0.3.0.dist-info/WHEEL
statqa-0.3.0.dist-info/entry_points.txt
statqa-0.3.0.dist-info/METADATA
statqa-0.3.0.dist-info/RECORD
