Metadata-Version: 2.4
Name: statqa
Version: 0.3.0
Summary: Automatically extract structured facts, insights, and Q/A pairs from tabular datasets
Keywords: data-analysis,statistics,table-qa,fact-extraction,llm,rag,data-science
Author: Gaurav Sood
License-Expression: MIT
Classifier: Development Status :: 4 - Beta
Classifier: Intended Audience :: Science/Research
Classifier: Intended Audience :: Developers
Classifier: Operating System :: OS Independent
Classifier: Programming Language :: Python :: 3
Classifier: Programming Language :: Python :: 3.12
Classifier: Programming Language :: Python :: 3.13
Classifier: Programming Language :: Python :: 3.14
Classifier: Topic :: Scientific/Engineering
Classifier: Topic :: Scientific/Engineering :: Information Analysis
Classifier: Typing :: Typed
Requires-Dist: pandas>=2.0.0
Requires-Dist: numpy>=1.24.0
Requires-Dist: scipy>=1.11.0
Requires-Dist: statsmodels>=0.14.0
Requires-Dist: matplotlib>=3.7.0
Requires-Dist: seaborn>=0.12.0
Requires-Dist: pydantic>=2.0.0
Requires-Dist: typer>=0.9.0
Requires-Dist: rich>=13.0.0
Requires-Dist: statqa[llm,pdf,statistical-formats,examples,dev,docs] ; extra == 'all'
Requires-Dist: pytest>=7.4.0 ; extra == 'dev'
Requires-Dist: pytest-cov>=4.1.0 ; extra == 'dev'
Requires-Dist: pytest-mock>=3.12.0 ; extra == 'dev'
Requires-Dist: pytest-asyncio>=0.21.0 ; extra == 'dev'
Requires-Dist: ruff>=0.1.0 ; extra == 'dev'
Requires-Dist: pydoclint>=0.3.8 ; extra == 'dev'
Requires-Dist: pyright>=1.1.390 ; extra == 'dev'
Requires-Dist: ipython>=8.12.0 ; extra == 'dev'
Requires-Dist: ipdb>=0.13.0 ; extra == 'dev'
Requires-Dist: sphinx>=7.0.0 ; extra == 'docs'
Requires-Dist: furo>=2024.7.18 ; extra == 'docs'
Requires-Dist: myst-parser>=2.0.0 ; extra == 'docs'
Requires-Dist: sphinx-autodoc-typehints>=1.24.0 ; extra == 'docs'
Requires-Dist: linkify-it-py>=2.0.0 ; extra == 'docs'
Requires-Dist: tqdm>=4.65.0 ; extra == 'examples'
Requires-Dist: openai>=1.0.0 ; extra == 'llm'
Requires-Dist: anthropic>=0.18.0 ; extra == 'llm'
Requires-Dist: pdfplumber>=0.10.0 ; extra == 'pdf'
Requires-Dist: pyreadstat>=1.3.0 ; extra == 'statistical-formats'
Requires-Python: >=3.12
Project-URL: Bug Tracker, https://github.com/gojiplus/statqa/issues
Project-URL: Documentation, https://gojiplus.github.io/statqa
Project-URL: Homepage, https://github.com/gojiplus/statqa
Project-URL: Repository, https://github.com/gojiplus/statqa
Provides-Extra: all
Provides-Extra: dev
Provides-Extra: docs
Provides-Extra: examples
Provides-Extra: llm
Provides-Extra: pdf
Provides-Extra: statistical-formats
